.gitignore
README.rst
setup.py
admin_langswitch/__init__.py
admin_langswitch/middleware.py
admin_langswitch/templates/admin/base.html
admin_langswitch/templates/admin/change_language.html
django_admin_langswitch.egg-info/PKG-INFO
django_admin_langswitch.egg-info/SOURCES.txt
django_admin_langswitch.egg-info/dependency_links.txt
django_admin_langswitch.egg-info/top_level.txt